doji/core/__init__.py
doji/core/api/__init__.py
doji/core/api/classes/__init__.py
doji/core/api/classes/api.py
doji/core/api/classes/api_response.py
doji/core/api/mixins/__init__.py
doji/core/api/mixins/api_mixin.py
doji/core/asset/__init__.py
doji/core/asset/classes/__init__.py
doji/core/asset/classes/asset.py
doji/core/asset/classes/asset_instances.py
doji/core/asset/classes/asset_pair.py
doji/core/asset/classes/asset_pair_instances.py
doji/core/asset/mixins/__init__.py
doji/core/asset/mixins/asset_pairs_mixin.py
doji/core/asset/mixins/assets_mixin.py
doji/core/currency/__init__.py
doji/core/currency/classes/__init__.py
doji/core/currency/classes/currency.py
doji/core/currency/classes/currency_instances.py
doji/core/currency/classes/currency_pair.py
doji/core/currency/classes/currency_pair_instances.py
doji/core/currency/mixins/__init__.py
doji/core/currency/mixins/currencies_mixin.py
doji/core/currency/mixins/currency_pairs_mixin.py
doji/core/exchange/__init__.py
doji/core/exchange/classes/__init__.py
doji/core/exchange/classes/currency_exchange.py
doji/core/exchange/classes/exchange.py
doji/core/py.typed
doji/core/types/__init__.py
doji/core/utils/__init__.py
doji/core/utils/classes/__init__.py
doji/core/utils/classes/instance.py
doji/core/utils/classes/instances.py
doji/core/utils/classes/nothing.py
doji/core/utils/functions/__init__.py
doji/core/utils/functions/dict.py
doji_core-0.1.6.dist-info/LICENSE
doji_core-0.1.6.dist-info/METADATA
doji_core-0.1.6.dist-info/WHEEL
doji_core-0.1.6.dist-info/RECORD
