Metadata-Version: 2.1
Name: doji-core
Version: 0.1.6
Summary: A repository for Doji, a trade analytics suite written in Python.
License: MIT
Author: Sean O'Leary
Author-email: seamicole@gmail.com
Requires-Python: >=3.10,<4.0
Classifier: License :: OSI Approved :: MIT License
Classifier: Programming Language :: Python :: 3
Classifier: Programming Language :: Python :: 3.10
Classifier: Programming Language :: Python :: 3.11
Requires-Dist: aiohttp (>=3.8.4,<4.0.0)
Requires-Dist: pydantic (>=1.10.7,<2.0.0)
Requires-Dist: requests (>=2.28.2,<3.0.0)
Requires-Dist: types-requests (>=2.28.11.17,<3.0.0.0)
